EasyCode/EasyCode.py
EasyCode/__init__.py
EasyCode-0.0.1.dist-info/METADATA
EasyCode-0.0.1.dist-info/WHEEL
EasyCode-0.0.1.dist-info/top_level.txt
EasyCode-0.0.1.dist-info/RECORD
