Metadata-Version: 2.1
Name: EasyCode
Version: 0.0.1
Summary: Easily write code
Home-page: UNKNOWN
Author: Python.Stuff
Author-email: <srinathngudi11@gmail.com>
License: UNKNOWN
Keywords: python,easy,code
Platform: UNKNOWN
Classifier: Development Status :: 1 - Planning
Classifier: Intended Audience :: Developers
Classifier: Programming Language :: Python :: 3
Classifier: Operating System :: Unix
Classifier: Operating System :: MacOS :: MacOS X
Classifier: Operating System :: Microsoft :: Windows
Requires-Dist: pyautogui
Requires-Dist: pyttsx3
Requires-Dist: speechrecognition
